{"ar":{"slug":"git-updater","language":"ar","updated":"2019-11-24 01:04+0300","package":"\/packages\/git-updater-ar.zip","autoupdate":"1"},"bg_BG":{"slug":"git-updater","language":"bg_BG","updated":"2018-12-01 09:18-0800","package":"\/packages\/git-updater-bg_BG.zip","autoupdate":"1"},"de_AT":{"slug":"git-updater","language":"de_AT","updated":"2018-12-01 09:18-0800","package":"\/packages\/git-updater-de_AT.zip","autoupdate":"1"},"de_CH":{"slug":"git-updater","language":"de_CH","updated":"2018-12-01 09:17-0800","package":"\/packages\/git-updater-de_CH.zip","autoupdate":"1"},"de_DE":{"slug":"git-updater","language":"de_DE","updated":"2022-03-15 15:09:43+0000","package":"\/packages\/git-updater-de_DE.zip","autoupdate":"1"},"es_ES":{"slug":"git-updater","language":"es_ES","updated":"2018-12-01 09:16-0800","package":"\/packages\/git-updater-es_ES.zip","autoupdate":"1"},"fr_FR":{"slug":"git-updater","language":"fr_FR","updated":"2022-03-14 16:39:38+0000","package":"\/packages\/git-updater-fr_FR.zip","autoupdate":"1"},"it":{"slug":"git-updater","language":"it","updated":"2022-10-15 15:58:04+0000","package":"\/packages\/git-updater-it.zip","autoupdate":"1"},"ja":{"slug":"git-updater","language":"ja","updated":"2018-12-01 09:15-0800","package":"\/packages\/git-updater-ja.zip","autoupdate":"1"},"pt_BR":{"slug":"git-updater","language":"pt_BR","updated":"2018-12-01 09:15-0800","package":"\/packages\/git-updater-pt_BR.zip","autoupdate":"1"},"pt_PT":{"slug":"git-updater","language":"pt_PT","updated":"2019-10-14 16:12+0100","package":"\/packages\/git-updater-pt_PT.zip","autoupdate":"1"},"ro_RO":{"slug":"git-updater","language":"ro_RO","updated":"2018-12-01 09:15-0800","package":"\/packages\/git-updater-ro_RO.zip","autoupdate":"1"},"ru_RU":{"slug":"git-updater","language":"ru_RU","updated":"2018-12-01 11:31+0500","package":"\/packages\/git-updater-ru_RU.zip","autoupdate":"1"},"sv_SE":{"slug":"git-updater","language":"sv_SE","updated":"2019-10-11 14:27+0200","package":"\/packages\/git-updater-sv_SE.zip","autoupdate":"1"},"uk":{"slug":"git-updater","language":"uk","updated":"2018-12-01 09:14-0800","package":"\/packages\/git-updater-uk.zip","autoupdate":"1"},"zh_TW":{"slug":"git-updater","language":"zh_TW","updated":"2021-06-16 01:47-0700","package":"\/packages\/git-updater-zh_TW.zip","autoupdate":"1"}}